explain_cli/__init__.py
explain_cli/cli.py
explain_cli/config.py
explain_cli/prompts.py
explain_cli/styles.py
explain_cli-1.1.0.dist-info/licenses/LICENSE
explain_cli-1.1.0.dist-info/METADATA
explain_cli-1.1.0.dist-info/WHEEL
explain_cli-1.1.0.dist-info/entry_points.txt
explain_cli-1.1.0.dist-info/top_level.txt
explain_cli-1.1.0.dist-info/RECORD
