Metadata-Version: 2.4
Name: explain-cli
Version: 1.1.0
Summary: Explain repo state with Claude Code or Gemini CLI
Author-email: ccmdi <ccmdi.dev@gmail.com>
License: MIT
Project-URL: Homepage, https://github.com/ccmdi/explain-cli
Project-URL: Repository, https://github.com/ccmdi/explain-cli
Project-URL: Issues, https://github.com/ccmdi/explain-cli/issues
Keywords: git,ai,cli,llm,explain
Classifier: Development Status :: 4 - Beta
Classifier: Intended Audience :: Developers
Classifier: License :: OSI Approved :: MIT License
Classifier: Programming Language :: Python :: 3
Classifier: Programming Language :: Python :: 3.11
Classifier: Topic :: Software Development :: Version Control :: Git
Classifier: Topic :: Software Development :: Libraries :: Python Modules
Requires-Python: >=3.7
License-File: LICENSE
Requires-Dist: pyperclip
Requires-Dist: inquirer
Requires-Dist: rich
Dynamic: license-file
